py_test_modulepd/__init__.py
py_test_modulepd-0.1.dist-info/METADATA
py_test_modulepd-0.1.dist-info/WHEEL
py_test_modulepd-0.1.dist-info/top_level.txt
py_test_modulepd-0.1.dist-info/RECORD
