Metadata-Version: 2.1
Name: py-test-modulepd
Version: 0.1
Summary: test d'arabe
Author: Landry Ingouf
Author-email: Landry.Ingoufdevelopper89@gmail.com
Classifier: Programming Language :: Python :: 3
Classifier: License :: OSI Approved :: MIT License
Classifier: Operating System :: OS Independent
